or_shifty/__init__.py
or_shifty/app.py
or_shifty/cli.py
or_shifty/config.py
or_shifty/constraints.py
or_shifty/history.py
or_shifty/history_metrics.py
or_shifty/indexer.py
or_shifty/model.py
or_shifty/objective.py
or_shifty/person.py
or_shifty/shift.py
or_shifty-1.1.0.dist-info/entry_points.txt
or_shifty-1.1.0.dist-info/LICENSE
or_shifty-1.1.0.dist-info/WHEEL
or_shifty-1.1.0.dist-info/METADATA
or_shifty-1.1.0.dist-info/RECORD
