Metadata-Version: 2.1
Name: or-shifty
Version: 1.1.0
Summary: 
Home-page: https://github.com/Dalamar42/or-shifty
License: MIT
Keywords: rota,scheduling,on-call
Author: Thomas Maroulis
Author-email: thomasmaroulis@gmail.com
Requires-Python: >=3.7,<4.0
Classifier: License :: OSI Approved :: MIT License
Classifier: Programming Language :: Python :: 3
Classifier: Programming Language :: Python :: 3.7
Classifier: Programming Language :: Python :: 3.8
Requires-Dist: ortools (>=7.2,<8.0)
Project-URL: Repository, https://github.com/Dalamar42/or-shifty
